{"name":"Pixelarticons","total":480,"version":"1.7.0","author":{"name":"Gerrit Halfmann","url":"https://github.com/halfmage/pixelarticons"},"license":{"title":"MIT","spdx":"MIT","url":"https://github.com/halfmage/pixelarticons/blob/master/LICENSE"},"samples":["drag-and-drop","arrows-horizontal","heart"],"height":24,"category":"General","palette":false,"id":"pixelarticons","icons":["4g","4k","4k-box","5g","ab-testing","ac","add-box","add-box-multiple","add-col","add-grid","add-row","alert","align-center","align-justify","align-left","align-right","analytics","anchor","android","animation","archive","arrow-bar-down","arrow-bar-left","arrow-bar-right","arrow-bar-up","arrow-down","arrow-down-box","arrow-left","arrow-left-box","arrow-right","arrow-right-box","arrow-up","arrow-up-box","arrows-horizontal","arrows-vertical","art-text","article","article-multiple","aspect-ratio","at","attachment","audio-device","avatar","backburger","battery","battery-1","battery-2","battery-charging","battery-full","bed","bitcoin","bluetooth","book","book-open","bookmark","bookmarks","briefcase","briefcase-account","briefcase-check","briefcase-delete","briefcase-download","briefcase-minus","briefcase-plus","briefcase-search","briefcase-search-1","briefcase-upload","bug","building","building-community","building-skyscraper","buildings","bulletlist","bullseye","bullseye-arrow","bus","cake","calculator","calendar","calendar-alert","calendar-arrow-left","calendar-arrow-right","calendar-check","calendar-export","calendar-grid","calendar-import","calendar-minus","calendar-month","calendar-multiple","calendar-multiple-check","calendar-plus","calendar-range","calendar-remove","calendar-search","calendar-sort-ascending","calendar-sort-descending","calendar-text","calendar-today","calendar-tomorrow","calendar-week","calendar-week-begin","calendar-weekend","camera","camera-add","camera-alt","camera-face","car","card","card-id","card-plus","card-stack","card-text","cart","cast","cellular-signal-0","cellular-signal-1","cellular-signal-2","cellular-signal-3","cellular-signal-off","chart","chart-add","chart-bar","chart-delete","chart-minus","chart-multiple","chat","check","check-double","checkbox","checkbox-on","checklist","chess","chevron-down","chevron-left","chevron-right","chevron-up","chevrons-horizontal","chevrons-vertical","circle","clipboard","clock","close","close-box","cloud","cloud-done","cloud-download","cloud-moon","cloud-sun","cloud-upload","cocktail","code","coffee","coffee-alt","coin","collapse","colors-swatch","command","comment","contact","contact-delete","contact-multiple","contact-plus","copy","corner-down-left","corner-down-right","corner-left-down","corner-left-up","corner-right-down","corner-right-up","corner-up-left","corner-up-right","credit-card","credit-card-delete","credit-card-minus","credit-card-multiple","credit-card-plus","credit-card-settings","credit-card-wireless","crop","cut","dashbaord","debug","debug-check","debug-off","debug-pause","debug-play","debug-stop","delete","deskphone","device-laptop","device-phone","device-tablet","device-tv","device-tv-smart","device-vibrate","device-watch","devices","dice","dollar","downasaur","download","draft","drag-and-drop","drop","drop-area","drop-full","drop-half","duplicate","duplicate-alt","edit","edit-box","euro","expand","external-link","eye","eye-closed","file","file-alt","file-delete","file-flash","file-minus","file-multiple","file-off","file-plus","fill","fill-half","flag","flatten","flip-to-back","flip-to-front","float-center","float-left","float-right","folder","folder-minus","folder-plus","folder-x","forward","forwardburger","frame","frame-add","frame-check","frame-delete","frame-minus","gamepad","gif","gift","git-branch","git-commit","git-merge","git-pull-request","gps","grid","group","hd","headphone","headset","heart","hidden","home","hourglass","hq","human","human-handsdown","human-handsup","human-height","human-height-alt","human-run","image","image-arrow-right","image-broken","image-delete","image-flash","image-frame","image-gallery","image-multiple","image-new","image-plus","inbox","inbox-all","inbox-full","info-box","invert","iso","kanban","keyboard","label","label-alt","label-alt-multiple","label-sharp","layout","layout-align-bottom","layout-align-left","layout-align-right","layout-align-top","layout-columns","layout-distribute-horizontal","layout-distribute-vertical","layout-footer","layout-header","layout-rows","layout-sidebar-left","layout-sidebar-right","link","list","list-box","loader","lock","lock-open","login","logout","luggage","mail","mail-arrow-right","mail-check","mail-delete","mail-flash","mail-multiple","mail-off","mail-unread","map","membercard","menu","message","message-arrow-left","message-arrow-right","message-bookmark","message-clock","message-delete","message-flash","message-image","message-minus","message-plus","message-processing","message-reply","message-text","minus","missed-call","modem","money","monitor","mood-happy","mood-neutral","mood-sad","moon","moon-star","moon-stars","more-horizontal","more-vertical","mouse","move","movie","music","next","note","note-delete","note-multiple","note-plus","notes","notes-delete","notes-multiple","notes-plus","notification","notification-off","open","paint-bucket","paperclip","pause","percent","picture-in-picture","picture-in-picture-alt","pin","pixelarticons","play","playlist","plus","power","prev","print","radio-handheld","radio-on","radio-signal","radio-tower","reciept","reciept-alt","redo","reload","remove-box","remove-box-multiple","repeat","reply","reply-all","rounded-corner","save","scale","script","script-text","scroll-horizontal","scroll-vertical","sd","search","section","section-copy","section-minus","section-plus","section-x","server","sharp-corner","shield","shield-off","ship","shopping-bag","shuffle","sliders","sliders-2","sort","sort-alpabetic","sort-numeric","speaker","speed-fast","speed-medium","speed-slow","spotlight","store","subscriptions","subtitles","suitcase","sun","sun-alt","switch","sync","tab","table","tea","teach","text-add","text-colums","text-search","text-wrap","timeline","toggle-left","toggle-right","tournament","track-changes","trash","trash-alt","trending","trending-down","trending-up","trophy","truck","undo","ungroup","unlink","upload","user","user-minus","user-plus","user-x","users","video","video-off","view-col","view-list","viewport-narrow","viewport-wide","visible","volume","volume-1","volume-2","volume-3","volume-minus","volume-plus","volume-vibrate","volume-x","wallet","warning-box","wind","zap","zoom-in","zoom-out"]}
